CROPS-0.1.1.data/scripts/crops-cropseq
CROPS-0.1.1.data/scripts/crops-cropstr
CROPS-0.1.1.data/scripts/crops-renumber
crops/__init__.py
crops/about.py
crops/command_line/__init__.py
crops/command_line/crops-cropseq.py
crops/command_line/crops-cropstr.py
crops/command_line/crops-renumber.py
crops/core/__init__.py
crops/core/ops.py
crops/elements/__init__.py
crops/elements/intervals.py
crops/elements/sequence.py
crops/io/__init__.py
crops/io/parsers.py
crops/io/taggers.py
crops/libs/__init__.py
crops/libs/rescodes.py
CROPS-0.1.1.dist-info/LICENSE
CROPS-0.1.1.dist-info/METADATA
CROPS-0.1.1.dist-info/WHEEL
CROPS-0.1.1.dist-info/top_level.txt
CROPS-0.1.1.dist-info/RECORD
