Metadata-Version: 2.1
Name: CROPS
Version: 0.1.1
Summary: Cropping and Renumbering Operations for PDB structure and Sequence files
Home-page: https://github.com/rigdenlab/crops
Author: J. Javier Burgos-Mármol
Author-email: J.J.Burgos-Marmol@liverpool.ac.uk
License: UNKNOWN
Platform: UNKNOWN
Classifier: Programming Language :: Python :: 3
Classifier: License :: OSI Approved :: BSD License
Classifier: Operating System :: OS Independent
Requires-Dist: gemmi (==0.4.3)
